{"payload":"{\"name\":\"gist: 826840\",\"desc\":\"Starcraft 2 counters for basic units (node)\",\"actor\":\"tantalor\",\"url\":\"https://gist.github.com/826840\",\"snippet\":\"var\\n  ZERGLING  = 'Zergling',\\n  ROACH     = 'Roach',\",\"actor_gravatar\":\"8134f2e2f24cf73b42d1b751582ba408\",\"action\":\"create\"}","public":true,"repo":{"url":"https://api.github.dev/repos//","name":"/"},"actor":{"id":1652,"login":"tantalor","gravatar_id":"8134f2e2f24cf73b42d1b751582ba408","avatar_url":"https://secure.gravatar.com/avatar/8134f2e2f24cf73b42d1b751582ba408?d=http://github.dev%2Fimages%2Fgravatars%2Fgravatar-user-420.png","url":"https://api.github.dev/users/tantalor"},"created_at":"2011-02-15 00:03:46","id":"1132229596","type":"GistEvent"}