{"actor":{"id":1437645,"login":"rautiocination","gravatar_id":"999bf99c57044f28f3e8d5f1cb4a0bfe","avatar_url":"https://secure.gravatar.com/avatar/999bf99c57044f28f3e8d5f1cb4a0bfe?d=http://github.dev%2Fimages%2Fgravatars%2Fgravatar-user-420.png","url":"https://api.github.dev/users/rautiocination"},"created_at":"2012-02-15 00:00:00","id":"1519871547","org":null,"other":{},"payload":"{\"action\":\"started\"}","public":true,"repo":{"id":117549,"url":"https://api.github.dev/repos/toastdriven/django-haystack","name":"toastdriven/django-haystack"},"type":"WatchEvent"}